pambas2.py
pambas2-0.2.dist-info/METADATA
pambas2-0.2.dist-info/WHEEL
pambas2-0.2.dist-info/top_level.txt
pambas2-0.2.dist-info/RECORD
